dvenv/__init__.py
dvenv/broker.py
dvenv/channel.py
dvenv/client.py
dvenv/commands/__init__.py
dvenv/commands/host.py
dvenv/commands/init.py
dvenv/config.py
dvenv/decorators.py
dvenv/exceptions.py
dvenv/log.py
dvenv/main.py
dvenv/runner.py
dvenv/server.py
dvenv/transact.py
dvenv-0.1.4.dist-info/entry_points.txt
dvenv-0.1.4.dist-info/WHEEL
dvenv-0.1.4.dist-info/METADATA
dvenv-0.1.4.dist-info/RECORD
